daraja/__init__.py
daraja/mpesa.py
daraja-0.0.3.dist-info/LICENSE
daraja-0.0.3.dist-info/METADATA
daraja-0.0.3.dist-info/WHEEL
daraja-0.0.3.dist-info/top_level.txt
daraja-0.0.3.dist-info/RECORD
