Metadata-Version: 2.1
Name: daraja
Version: 0.0.3
Summary: a simple to use mpesa module around the daraja api
Author-email: John Gitahi <gitahi109@gmail.com>
Project-URL: Homepage, https://github.com/johngitahi/daraja.py
Project-URL: Bug Tracker, https://github.com/johngitahi/daraja.py/issues
Classifier: Programming Language :: Python :: 3
Classifier: License :: OSI Approved :: zlib/libpng License
Classifier: Operating System :: OS Independent
Requires-Python: >=3.7
License-File: LICENSE
